formcrypt/__init__.py
formcrypt/__main__.py
formcrypt/cli.py
formcrypt/core.py
formcrypt/sourcefile.py
formcrypt/terminal.py
formcrypt/utils.py
formcrypt/rsrc/formcrypt.c
formcrypt/rsrc/formcrypt.h
formcrypt-2.0.0.dist-info/METADATA
formcrypt-2.0.0.dist-info/WHEEL
formcrypt-2.0.0.dist-info/entry_points.txt
formcrypt-2.0.0.dist-info/RECORD
