Metadata-Version: 2.4
Name: formcrypt
Version: 2.0.0
Summary: A utility for encrypting / decrypting strings in C/C++ implants, based on a similar technique form the FormBook malware.
Project-URL: Github, https://github.com/wizardy0ga/formcrypt
Author: wizardy0ga
Requires-Python: >=3.10
